MANIFEST.in
setup.py
pyfanova/__init__.py
pyfanova/config_space.py
pyfanova/example.py
pyfanova/fanova.py
pyfanova/fanova_from_csv.py
pyfanova/fanova_from_hpolib.py
pyfanova/fanova_remote.py
pyfanova/visualizer.py
pyfanova.egg-info/PKG-INFO
pyfanova.egg-info/SOURCES.txt
pyfanova.egg-info/dependency_links.txt
pyfanova.egg-info/requires.txt
pyfanova.egg-info/top_level.txt
pyfanova/fanova/DomainInter.jar
pyfanova/fanova/Jama-1.0.2.jar
pyfanova/fanova/aclib-src.jar
pyfanova/fanova/aclib.jar
pyfanova/fanova/commons-collections-3.2.1.jar
pyfanova/fanova/commons-io-2.1.jar
pyfanova/fanova/commons-math-2.2.jar
pyfanova/fanova/commons-math3-3.2.jar
pyfanova/fanova/exp4j-0.3.10.jar
pyfanova/fanova/fanova.jar
pyfanova/fanova/fastrf-src.jar
pyfanova/fanova/fastrf.jar
pyfanova/fanova/guava-14.0.1.jar
pyfanova/fanova/jcip-annotations-src.jar
pyfanova/fanova/jcip-annotations.jar
pyfanova/fanova/jcommander.jar
pyfanova/fanova/logback-access-1.0.13.jar
pyfanova/fanova/logback-classic-1.0.13.jar
pyfanova/fanova/logback-core-1.0.13.jar
pyfanova/fanova/numerics4j-1.3.jar
pyfanova/fanova/opencsv-2.3.jar
pyfanova/fanova/slf4j-api-1.7.5.jar
pyfanova/fanova/spi-0.2.4.jar